{"nym:AE-AJ":{"edges":{"from":["territory:AE-AJ"]},"meta":{"canonical":false,"canonical-mask":0,"display-name":false,"stable-name":false},"names":{"cy":false,"en-GB":"AE-AJ"}},"nym:Emirate of Ajman":{"edges":{"from":["territory:AE-AJ"]},"meta":{"canonical":false,"canonical-mask":0,"display-name":true,"stable-name":true},"names":{"cy":false,"en-GB":"Emirate of Ajman"}},"territory:AE-AJ":{"edges":{"from":[]},"meta":{"canonical":true,"canonical-mask":1,"display-name":true,"stable-name":true},"names":{"cy":false,"en-GB":"Ajman"}},"nym:AE-AZ":{"edges":{"from":["territory:AE-AZ"]},"meta":{"canonical":false,"canonical-mask":0,"display-name":false,"stable-name":false},"names":{"cy":false,"en-GB":"AE-AZ"}},"nym:Emirate of Abu Dhabi":{"edges":{"from":["territory:AE-AZ"]},"meta":{"canonical":false,"canonical-mask":0,"display-name":true,"stable-name":true},"names":{"cy":false,"en-GB":"Emirate of Abu Dhabi"}},"territory:AE-AZ":{"edges":{"from":[]},"meta":{"canonical":true,"canonical-mask":1,"display-name":true,"stable-name":true},"names":{"cy":false,"en-GB":"Abu Dhabi"}},"nym:AE-DU":{"edges":{"from":["territory:AE-DU"]},"meta":{"canonical":false,"canonical-mask":0,"display-name":false,"stable-name":false},"names":{"cy":false,"en-GB":"AE-DU"}},"nym:Emirate of Dubai":{"edges":{"from":["territory:AE-DU"]},"meta":{"canonical":false,"canonical-mask":0,"display-name":true,"stable-name":true},"names":{"cy":false,"en-GB":"Emirate of Dubai"}},"territory:AE-DU":{"edges":{"from":[]},"meta":{"canonical":true,"canonical-mask":1,"display-name":true,"stable-name":true},"names":{"cy":false,"en-GB":"Dubai"}},"nym:AE-FU":{"edges":{"from":["territory:AE-FU"]},"meta":{"canonical":false,"canonical-mask":0,"display-name":false,"stable-name":false},"names":{"cy":false,"en-GB":"AE-FU"}},"nym:Emirate of Fujairah":{"edges":{"from":["territory:AE-FU"]},"meta":{"canonical":false,"canonical-mask":0,"display-name":true,"stable-name":true},"names":{"cy":false,"en-GB":"Emirate of Fujairah"}},"territory:AE-FU":{"edges":{"from":[]},"meta":{"canonical":true,"canonical-mask":1,"display-name":true,"stable-name":true},"names":{"cy":false,"en-GB":"Fujairah"}},"nym:AE-RK":{"edges":{"from":["territory:AE-RK"]},"meta":{"canonical":false,"canonical-mask":0,"display-name":false,"stable-name":false},"names":{"cy":false,"en-GB":"AE-RK"}},"nym:Emirate of Ras al-Khaimah":{"edges":{"from":["territory:AE-RK"]},"meta":{"canonical":false,"canonical-mask":0,"display-name":true,"stable-name":true},"names":{"cy":false,"en-GB":"Emirate of Ras al-Khaimah"}},"territory:AE-RK":{"edges":{"from":[]},"meta":{"canonical":true,"canonical-mask":1,"display-name":true,"stable-name":true},"names":{"cy":false,"en-GB":"Ras al-Khaimah"}},"nym:AE-SH":{"edges":{"from":["territory:AE-SH"]},"meta":{"canonical":false,"canonical-mask":0,"display-name":false,"stable-name":false},"names":{"cy":false,"en-GB":"AE-SH"}},"nym:Emirate of Sharjah":{"edges":{"from":["territory:AE-SH"]},"meta":{"canonical":false,"canonical-mask":0,"display-name":true,"stable-name":true},"names":{"cy":false,"en-GB":"Emirate of Sharjah"}},"territory:AE-SH":{"edges":{"from":[]},"meta":{"canonical":true,"canonical-mask":1,"display-name":true,"stable-name":true},"names":{"cy":false,"en-GB":"Sharjah"}},"nym:AE-UQ":{"edges":{"from":["territory:AE-UQ"]},"meta":{"canonical":false,"canonical-mask":0,"display-name":false,"stable-name":false},"names":{"cy":false,"en-GB":"AE-UQ"}},"nym:Emirate of Umm al-Quwain":{"edges":{"from":["territory:AE-UQ"]},"meta":{"canonical":false,"canonical-mask":0,"display-name":true,"stable-name":true},"names":{"cy":false,"en-GB":"Emirate of Umm al-Quwain"}},"territory:AE-UQ":{"edges":{"from":[]},"meta":{"canonical":true,"canonical-mask":1,"display-name":true,"stable-name":true},"names":{"cy":false,"en-GB":"Umm al-Quwain"}},"nym:AI":{"edges":{"from":["territory:AI"]},"meta":{"canonical":false,"canonical-mask":0,"display-name":false,"stable-name":false},"names":{"cy":false,"en-GB":"AI"}},"nym:Anguilla":{"edges":{"from":["territory:AI"]},"meta":{"canonical":false,"canonical-mask":0,"display-name":true,"stable-name":true},"names":{"cy":false,"en-GB":"Anguilla"}},"territory:AI":{"edges":{"from":[]},"meta":{"canonical":true,"canonical-mask":1,"display-name":true,"stable-name":true},"names":{"cy":false,"en-GB":"Anguilla"}},"nym:AQ":{"edges":{"from":["territory:AQ"]},"meta":{"canonical":false,"canonical-mask":0,"display-name":false,"stable-name":false},"names":{"cy":false,"en-GB":"AQ"}},"nym:Antarctica":{"edges":{"from":["territory:AQ"]},"meta":{"canonical":false,"canonical-mask":0,"display-name":true,"stable-name":true},"names":{"cy":false,"en-GB":"Antarctica"}},"territory:AQ":{"edges":{"from":[]},"meta":{"canonical":true,"canonical-mask":1,"display-name":true,"stable-name":true},"names":{"cy":false,"en-GB":"Antarctica"}},"nym:AS":{"edges":{"from":["territory:AS"]},"meta":{"canonical":false,"canonical-mask":0,"display-name":false,"stable-name":false},"names":{"cy":false,"en-GB":"AS"}},"nym:Eastern Samoa":{"edges":{"from":["territory:AS"]},"meta":{"canonical":false,"canonical-mask":0,"display-name":false,"stable-name":false},"names":{"cy":false,"en-GB":"Eastern Samoa"}},"nym:Territory of American Samoa":{"edges":{"from":["territory:AS"]},"meta":{"canonical":false,"canonical-mask":0,"display-name":true,"stable-name":true},"names":{"cy":false,"en-GB":"Territory of American Samoa"}},"territory:AS":{"edges":{"from":[]},"meta":{"canonical":true,"canonical-mask":1,"display-name":true,"stable-name":true},"names":{"cy":false,"en-GB":"American Samoa"}},"nym:AW":{"edges":{"from":["territory:AW"]},"meta":{"canonical":false,"canonical-mask":0,"display-name":false,"stable-name":false},"names":{"cy":false,"en-GB":"AW"}},"nym:Aruba":{"edges":{"from":["territory:AW"]},"meta":{"canonical":false,"canonical-mask":0,"display-name":true,"stable-name":true},"names":{"cy":false,"en-GB":"Aruba"}},"territory:AW":{"edges":{"from":[]},"meta":{"canonical":true,"canonical-mask":1,"display-name":true,"stable-name":true},"names":{"cy":false,"en-GB":"Aruba"}},"nym:AX":{"edges":{"from":["territory:AX"]},"meta":{"canonical":false,"canonical-mask":0,"display-name":false,"stable-name":false},"names":{"cy":false,"en-GB":"AX"}},"nym:Aaland":{"edges":{"from":["territory:AX"]},"meta":{"canonical":false,"canonical-mask":0,"display-name":false,"stable-name":false},"names":{"cy":false,"en-GB":"Aaland"}},"nym:Ahvenanmaa":{"edges":{"from":["territory:AX"]},"meta":{"canonical":false,"canonical-mask":0,"display-name":false,"stable-name":false},"names":{"cy":false,"en-GB":"Ahvenanmaa"}},"nym:Aland":{"edges":{"from":["territory:AX"]},"meta":{"canonical":false,"canonical-mask":0,"display-name":false,"stable-name":false},"names":{"cy":false,"en-GB":"Aland"}},"nym:Åland":{"edges":{"from":["territory:AX"]},"meta":{"canonical":false,"canonical-mask":0,"display-name":false,"stable-name":false},"names":{"cy":false,"en-GB":"Åland"}},"nym:Åland Islands":{"edges":{"from":["territory:AX"]},"meta":{"canonical":false,"canonical-mask":0,"display-name":true,"stable-name":true},"names":{"cy":false,"en-GB":"Åland Islands"}},"territory:AX":{"edges":{"from":[]},"meta":{"canonical":true,"canonical-mask":1,"display-name":true,"stable-name":true},"names":{"cy":false,"en-GB":"Åland Islands"}},"nym:BAT":{"edges":{"from":["territory:BAT"]},"meta":{"canonical":false,"canonical-mask":0,"display-name":false,"stable-name":false},"names":{"cy":false,"en-GB":"BAT"}},"nym:British Antarctic Territory":{"edges":{"from":["territory:BAT"]},"meta":{"canonical":false,"canonical-mask":0,"display-name":true,"stable-name":true},"names":{"cy":false,"en-GB":"British Antarctic Territory"}},"territory:BAT":{"edges":{"from":[]},"meta":{"canonical":true,"canonical-mask":1,"display-name":true,"stable-name":true},"names":{"cy":false,"en-GB":"British Antarctic Territory"}},"nym:BL":{"edges":{"from":["territory:BL"]},"meta":{"canonical":false,"canonical-mask":0,"display-name":false,"stable-name":false},"names":{"cy":false,"en-GB":"BL"}},"nym:Saint Barthélemy":{"edges":{"from":["territory:BL"]},"meta":{"canonical":false,"canonical-mask":0,"display-name":true,"stable-name":true},"names":{"cy":false,"en-GB":"Saint Barthélemy"}},"nym:St Barth":{"edges":{"from":["territory:BL"]},"meta":{"canonical":false,"canonical-mask":0,"display-name":false,"stable-name":false},"names":{"cy":false,"en-GB":"St Barth"}},"nym:St. Barthelemy":{"edges":{"from":["territory:BL"]},"meta":{"canonical":false,"canonical-mask":0,"display-name":false,"stable-name":false},"names":{"cy":false,"en-GB":"St. Barthelemy"}},"territory:BL":{"edges":{"from":[]},"meta":{"canonical":true,"canonical-mask":1,"display-name":true,"stable-name":true},"names":{"cy":false,"en-GB":"Saint Barthélemy"}},"nym:BM":{"edges":{"from":["territory:BM"]},"meta":{"canonical":false,"canonical-mask":0,"display-name":false,"stable-name":false},"names":{"cy":false,"en-GB":"BM"}},"nym:Bermuda":{"edges":{"from":["territory:BM"]},"meta":{"canonical":false,"canonical-mask":0,"display-name":true,"stable-name":true},"names":{"cy":false,"en-GB":"Bermuda"}},"nym:Bermudas":{"edges":{"from":["territory:BM"]},"meta":{"canonical":false,"canonical-mask":0,"display-name":false,"stable-name":false},"names":{"cy":false,"en-GB":"Bermudas"}},"territory:BM":{"edges":{"from":[]},"meta":{"canonical":true,"canonical-mask":1,"display-name":true,"stable-name":true},"names":{"cy":false,"en-GB":"Bermuda"}},"nym:BQ-BO":{"edges":{"from":["territory:BQ-BO"]},"meta":{"canonical":false,"canonical-mask":0,"display-name":false,"stable-name":false},"names":{"cy":false,"en-GB":"BQ-BO"}},"nym:Bonaire":{"edges":{"from":["territory:BQ-BO"]},"meta":{"canonical":false,"canonical-mask":0,"display-name":true,"stable-name":true},"names":{"cy":false,"en-GB":"Bonaire"}},"territory:BQ-BO":{"edges":{"from":[]},"meta":{"canonical":true,"canonical-mask":1,"display-name":true,"stable-name":true},"names":{"cy":false,"en-GB":"Bonaire"}},"nym:BQ-SA":{"edges":{"from":["territory:BQ-SA"]},"meta":{"canonical":false,"canonical-mask":0,"display-name":false,"stable-name":false},"names":{"cy":false,"en-GB":"BQ-SA"}},"nym:Saba":{"edges":{"from":["territory:BQ-SA"]},"meta":{"canonical":false,"canonical-mask":0,"display-name":true,"stable-name":true},"names":{"cy":false,"en-GB":"Saba"}},"territory:BQ-SA":{"edges":{"from":[]},"meta":{"canonical":true,"canonical-mask":1,"display-name":true,"stable-name":true},"names":{"cy":false,"en-GB":"Saba"}},"nym:BQ-SE":{"edges":{"from":["territory:BQ-SE"]},"meta":{"canonical":false,"canonical-mask":0,"display-name":false,"stable-name":false},"names":{"cy":false,"en-GB":"BQ-SE"}},"nym:Sint Eustatius":{"edges":{"from":["territory:BQ-SE"]},"meta":{"canonical":false,"canonical-mask":0,"display-name":true,"stable-name":true},"names":{"cy":false,"en-GB":"Sint Eustatius"}},"territory:BQ-SE":{"edges":{"from":[]},"meta":{"canonical":true,"canonical-mask":1,"display-name":true,"stable-name":true},"names":{"cy":false,"en-GB":"Sint Eustatius"}},"nym:BV":{"edges":{"from":["territory:BV"]},"meta":{"canonical":false,"canonical-mask":0,"display-name":false,"stable-name":false},"names":{"cy":false,"en-GB":"BV"}},"nym:Bouvet Island":{"edges":{"from":["territory:BV"]},"meta":{"canonical":false,"canonical-mask":0,"display-name":true,"stable-name":true},"names":{"cy":false,"en-GB":"Bouvet Island"}},"territory:BV":{"edges":{"from":[]},"meta":{"canonical":true,"canonical-mask":1,"display-name":true,"stable-name":true},"names":{"cy":false,"en-GB":"Bouvet Island"}},"nym:CC":{"edges":{"from":["territory:CC"]},"meta":{"canonical":false,"canonical-mask":0,"display-name":false,"stable-name":false},"names":{"cy":false,"en-GB":"CC"}},"nym:Territory of the Cocos (Keeling) Islands":{"edges":{"from":["territory:CC"]},"meta":{"canonical":false,"canonical-mask":0,"display-name":true,"stable-name":true},"names":{"cy":false,"en-GB":"Territory of the Cocos (Keeling) Islands"}},"territory:CC":{"edges":{"from":[]},"meta":{"canonical":true,"canonical-mask":1,"display-name":true,"stable-name":true},"names":{"cy":false,"en-GB":"Cocos (Keeling) Islands"}},"nym:CK":{"edges":{"from":["territory:CK"]},"meta":{"canonical":false,"canonical-mask":0,"display-name":false,"stable-name":false},"names":{"cy":false,"en-GB":"CK"}},"nym:Cook Islands":{"edges":{"from":["territory:CK"]},"meta":{"canonical":false,"canonical-mask":0,"display-name":false,"stable-name":false},"names":{"cy":false,"en-GB":"Cook Islands"}},"territory:CK":{"edges":{"from":[]},"meta":{"canonical":true,"canonical-mask":1,"display-name":true,"stable-name":true},"names":{"cy":false,"en-GB":"Cook Islands"}},"nym:CW":{"edges":{"from":["territory:CW"]},"meta":{"canonical":false,"canonical-mask":0,"display-name":false,"stable-name":false},"names":{"cy":false,"en-GB":"CW"}},"nym:Country of Curaçao":{"edges":{"from":["territory:CW"]},"meta":{"canonical":false,"canonical-mask":0,"display-name":true,"stable-name":true},"names":{"cy":false,"en-GB":"Country of Curaçao"}},"nym:Curacao":{"edges":{"from":["territory:CW"]},"meta":{"canonical":false,"canonical-mask":0,"display-name":false,"stable-name":false},"names":{"cy":false,"en-GB":"Curacao"}},"nym:Curaçao":{"edges":{"from":["territory:CW"]},"meta":{"canonical":false,"canonical-mask":0,"display-name":false,"stable-name":false},"names":{"cy":false,"en-GB":"Curaçao"}},"nym:Kòrsou":{"edges":{"from":["territory:CW"]},"meta":{"canonical":false,"canonical-mask":0,"display-name":false,"stable-name":false},"names":{"cy":false,"en-GB":"Kòrsou"}},"territory:CW":{"edges":{"from":[]},"meta":{"canonical":true,"canonical-mask":1,"display-name":true,"stable-name":true},"names":{"cy":false,"en-GB":"Curaçao"}},"nym:CX":{"edges":{"from":["territory:CX"]},"meta":{"canonical":false,"canonical-mask":0,"display-name":false,"stable-name":false},"names":{"cy":false,"en-GB":"CX"}},"nym:Territory of Christmas Island":{"edges":{"from":["territory:CX"]},"meta":{"canonical":false,"canonical-mask":0,"display-name":true,"stable-name":true},"names":{"cy":false,"en-GB":"Territory of Christmas Island"}},"territory:CX":{"edges":{"from":[]},"meta":{"canonical":true,"canonical-mask":1,"display-name":true,"stable-name":true},"names":{"cy":false,"en-GB":"Christmas Island"}},"nym:EH":{"edges":{"from":["territory:EH"]},"meta":{"canonical":false,"canonical-mask":0,"display-name":false,"stable-name":false},"names":{"cy":false,"en-GB":"EH"}},"nym:Western Sahara":{"edges":{"from":["territory:EH"]},"meta":{"canonical":false,"canonical-mask":0,"display-name":false,"stable-name":false},"names":{"cy":false,"en-GB":"Western Sahara"}},"nym:لصحراء الغربية":{"edges":{"from":["territory:EH"]},"meta":{"canonical":false,"canonical-mask":0,"display-name":false,"stable-name":false},"names":{"cy":false,"en-GB":"لصحراء الغربية"}},"territory:EH":{"edges":{"from":[]},"meta":{"canonical":true,"canonical-mask":1,"display-name":true,"stable-name":true},"names":{"cy":false,"en-GB":"Western Sahara"}},"nym:Ceuta":{"edges":{"from":["territory:ES-CE"]},"meta":{"canonical":false,"canonical-mask":0,"display-name":true,"stable-name":true},"names":{"cy":false,"en-GB":"Ceuta"}},"nym:ES-CE":{"edges":{"from":["territory:ES-CE"]},"meta":{"canonical":false,"canonical-mask":0,"display-name":false,"stable-name":false},"names":{"cy":false,"en-GB":"ES-CE"}},"territory:ES-CE":{"edges":{"from":[]},"meta":{"canonical":true,"canonical-mask":1,"display-name":true,"stable-name":true},"names":{"cy":false,"en-GB":"Ceuta"}},"nym:ES-ML":{"edges":{"from":["territory:ES-ML"]},"meta":{"canonical":false,"canonical-mask":0,"display-name":false,"stable-name":false},"names":{"cy":false,"en-GB":"ES-ML"}},"nym:Melilla":{"edges":{"from":["territory:ES-ML"]},"meta":{"canonical":false,"canonical-mask":0,"display-name":true,"stable-name":true},"names":{"cy":false,"en-GB":"Melilla"}},"territory:ES-ML":{"edges":{"from":[]},"meta":{"canonical":true,"canonical-mask":1,"display-name":true,"stable-name":true},"names":{"cy":false,"en-GB":"Melilla"}},"nym:FK":{"edges":{"from":["territory:FK"]},"meta":{"canonical":false,"canonical-mask":0,"display-name":false,"stable-name":false},"names":{"cy":false,"en-GB":"FK"}},"nym:Falkland Islands":{"edges":{"from":["territory:FK"]},"meta":{"canonical":false,"canonical-mask":0,"display-name":true,"stable-name":true},"names":{"cy":false,"en-GB":"Falkland Islands"}},"nym:Las Malvinas":{"edges":{"from":["territory:FK"]},"meta":{"canonical":false,"canonical-mask":0,"display-name":false,"stable-name":false},"names":{"cy":false,"en-GB":"Las Malvinas"}},"territory:FK":{"edges":{"from":[]},"meta":{"canonical":true,"canonical-mask":1,"display-name":true,"stable-name":true},"names":{"cy":false,"en-GB":"Falkland Islands"}},"nym:Aeroes":{"edges":{"from":["territory:FO"]},"meta":{"canonical":false,"canonical-mask":0,"display-name":false,"stable-name":false},"names":{"cy":false,"en-GB":"Aeroes"}},"nym:FO":{"edges":{"from":["territory:FO"]},"meta":{"canonical":false,"canonical-mask":0,"display-name":false,"stable-name":false},"names":{"cy":false,"en-GB":"FO"}},"nym:Faroe Islands":{"edges":{"from":["territory:FO"]},"meta":{"canonical":false,"canonical-mask":0,"display-name":true,"stable-name":true},"names":{"cy":false,"en-GB":"Faroe Islands"}},"nym:Faroes":{"edges":{"from":["territory:FO"]},"meta":{"canonical":false,"canonical-mask":0,"display-name":false,"stable-name":false},"names":{"cy":false,"en-GB":"Faroes"}},"nym:Færøerne":{"edges":{"from":["territory:FO"]},"meta":{"canonical":false,"canonical-mask":0,"display-name":false,"stable-name":false},"names":{"cy":false,"en-GB":"Færøerne"}},"nym:Føroyar":{"edges":{"from":["territory:FO"]},"meta":{"canonical":false,"canonical-mask":0,"display-name":false,"stable-name":false},"names":{"cy":false,"en-GB":"Føroyar"}},"territory:FO":{"edges":{"from":[]},"meta":{"canonical":true,"canonical-mask":1,"display-name":true,"stable-name":true},"names":{"cy":false,"en-GB":"Faroe Islands"}},"nym:French Guiana":{"edges":{"from":["territory:GF"]},"meta":{"canonical":false,"canonical-mask":0,"display-name":true,"stable-name":true},"names":{"cy":false,"en-GB":"French Guiana"}},"nym:GF":{"edges":{"from":["territory:GF"]},"meta":{"canonical":false,"canonical-mask":0,"display-name":false,"stable-name":false},"names":{"cy":false,"en-GB":"GF"}},"nym:Guyane":{"edges":{"from":["territory:GF"]},"meta":{"canonical":false,"canonical-mask":0,"display-name":false,"stable-name":false},"names":{"cy":false,"en-GB":"Guyane"}},"territory:GF":{"edges":{"from":[]},"meta":{"canonical":true,"canonical-mask":1,"display-name":true,"stable-name":true},"names":{"cy":false,"en-GB":"French Guiana"}},"nym:Bailiwick of Guernsey":{"edges":{"from":["territory:GG"]},"meta":{"canonical":false,"canonical-mask":0,"display-name":true,"stable-name":true},"names":{"cy":false,"en-GB":"Bailiwick of Guernsey"}},"nym:GG":{"edges":{"from":["territory:GG"]},"meta":{"canonical":false,"canonical-mask":0,"display-name":false,"stable-name":false},"names":{"cy":false,"en-GB":"GG"}},"nym:Island of Guernsey":{"edges":{"from":["territory:GG"]},"meta":{"canonical":false,"canonical-mask":0,"display-name":false,"stable-name":false},"names":{"cy":false,"en-GB":"Island of Guernsey"}},"territory:GG":{"edges":{"from":[]},"meta":{"canonical":true,"canonical-mask":1,"display-name":true,"stable-name":true},"names":{"cy":false,"en-GB":"Guernsey"}},"nym:GI":{"edges":{"from":["territory:GI"]},"meta":{"canonical":false,"canonical-mask":0,"display-name":false,"stable-name":false},"names":{"cy":false,"en-GB":"GI"}},"nym:Gibraltar":{"edges":{"from":["territory:GI"]},"meta":{"canonical":false,"canonical-mask":0,"display-name":true,"stable-name":true},"names":{"cy":false,"en-GB":"Gibraltar"}},"territory:GI":{"edges":{"from":[]},"meta":{"canonical":true,"canonical-mask":1,"display-name":true,"stable-name":true},"names":{"cy":false,"en-GB":"Gibraltar"}},"nym:GL":{"edges":{"from":["territory:GL"]},"meta":{"canonical":false,"canonical-mask":0,"display-name":false,"stable-name":false},"names":{"cy":false,"en-GB":"GL"}},"nym:Greenland":{"edges":{"from":["territory:GL"]},"meta":{"canonical":false,"canonical-mask":0,"display-name":true,"stable-name":true},"names":{"cy":false,"en-GB":"Greenland"}},"nym:Gronland":{"edges":{"from":["territory:GL"]},"meta":{"canonical":false,"canonical-mask":0,"display-name":false,"stable-name":false},"names":{"cy":false,"en-GB":"Gronland"}},"nym:Grønland":{"edges":{"from":["territory:GL"]},"meta":{"canonical":false,"canonical-mask":0,"display-name":false,"stable-name":false},"names":{"cy":false,"en-GB":"Grønland"}},"nym:Kalaallit Nunaat":{"edges":{"from":["territory:GL"]},"meta":{"canonical":false,"canonical-mask":0,"display-name":false,"stable-name":false},"names":{"cy":false,"en-GB":"Kalaallit Nunaat"}},"territory:GL":{"edges":{"from":[]},"meta":{"canonical":true,"canonical-mask":1,"display-name":true,"stable-name":true},"names":{"cy":false,"en-GB":"Greenland"}},"nym:GP":{"edges":{"from":["territory:GP"]},"meta":{"canonical":false,"canonical-mask":0,"display-name":false,"stable-name":false},"names":{"cy":false,"en-GB":"GP"}},"nym:Guadeloupe":{"edges":{"from":["territory:GP"]},"meta":{"canonical":false,"canonical-mask":0,"display-name":true,"stable-name":true},"names":{"cy":false,"en-GB":"Guadeloupe"}},"territory:GP":{"edges":{"from":[]},"meta":{"canonical":true,"canonical-mask":1,"display-name":true,"stable-name":true},"names":{"cy":false,"en-GB":"Guadeloupe"}},"nym:GS":{"edges":{"from":["territory:GS"]},"meta":{"canonical":false,"canonical-mask":0,"display-name":false,"stable-name":false},"names":{"cy":false,"en-GB":"GS"}},"nym:South Georgia and the South Sandwich Islands":{"edges":{"from":["territory:GS"]},"meta":{"canonical":false,"canonical-mask":0,"display-name":true,"stable-name":true},"names":{"cy":false,"en-GB":"South Georgia and the South Sandwich Islands"}},"territory:GS":{"edges":{"from":[]},"meta":{"canonical":true,"canonical-mask":1,"display-name":true,"stable-name":true},"names":{"cy":false,"en-GB":"South Georgia and South Sandwich Islands"}},"nym:GU":{"edges":{"from":["territory:GU"]},"meta":{"canonical":false,"canonical-mask":0,"display-name":false,"stable-name":false},"names":{"cy":false,"en-GB":"GU"}},"nym:Guåhån":{"edges":{"from":["territory:GU"]},"meta":{"canonical":false,"canonical-mask":0,"display-name":false,"stable-name":false},"names":{"cy":false,"en-GB":"Guåhån"}},"nym:Territory of Guam":{"edges":{"from":["territory:GU"]},"meta":{"canonical":false,"canonical-mask":0,"display-name":true,"stable-name":true},"names":{"cy":false,"en-GB":"Territory of Guam"}},"territory:GU":{"edges":{"from":[]},"meta":{"canonical":true,"canonical-mask":1,"display-name":true,"stable-name":true},"names":{"cy":false,"en-GB":"Guam"}},"nym:HK":{"edges":{"from":["territory:HK"]},"meta":{"canonical":false,"canonical-mask":0,"display-name":false,"stable-name":false},"names":{"cy":false,"en-GB":"HK"}},"nym:Heung Gong":{"edges":{"from":["territory:HK"]},"meta":{"canonical":false,"canonical-mask":0,"display-name":false,"stable-name":false},"names":{"cy":false,"en-GB":"Heung Gong"}},"nym:Hong Kong Special Administrative Region":{"edges":{"from":["territory:HK"]},"meta":{"canonical":false,"canonical-mask":0,"display-name":true,"stable-name":true},"names":{"cy":false,"en-GB":"Hong Kong Special Administrative Region"}},"nym:香港":{"edges":{"from":["territory:HK"]},"meta":{"canonical":false,"canonical-mask":0,"display-name":false,"stable-name":false},"names":{"cy":false,"en-GB":"香港"}},"territory:HK":{"edges":{"from":[]},"meta":{"canonical":true,"canonical-mask":1,"display-name":true,"stable-name":true},"names":{"cy":false,"en-GB":"Hong Kong"}},"nym:HM":{"edges":{"from":["territory:HM"]},"meta":{"canonical":false,"canonical-mask":0,"display-name":false,"stable-name":false},"names":{"cy":false,"en-GB":"HM"}},"nym:Territory of Heard Island and McDonald Islands":{"edges":{"from":["territory:HM"]},"meta":{"canonical":false,"canonical-mask":0,"display-name":true,"stable-name":true},"names":{"cy":false,"en-GB":"Territory of Heard Island and McDonald Islands"}},"territory:HM":{"edges":{"from":[]},"meta":{"canonical":true,"canonical-mask":1,"display-name":true,"stable-name":true},"names":{"cy":false,"en-GB":"Heard Island and McDonald Islands"}},"nym:Ellan Vannin":{"edges":{"from":["territory:IM"]},"meta":{"canonical":false,"canonical-mask":0,"display-name":false,"stable-name":false},"names":{"cy":false,"en-GB":"Ellan Vannin"}},"nym:IM":{"edges":{"from":["territory:IM"]},"meta":{"canonical":false,"canonical-mask":0,"display-name":false,"stable-name":false},"names":{"cy":false,"en-GB":"IM"}},"nym:Isle of Man":{"edges":{"from":["territory:IM"]},"meta":{"canonical":false,"canonical-mask":0,"display-name":true,"stable-name":true},"names":{"cy":false,"en-GB":"Isle of Man"}},"territory:IM":{"edges":{"from":[]},"meta":{"canonical":true,"canonical-mask":1,"display-name":true,"stable-name":true},"names":{"cy":false,"en-GB":"Isle of Man"}},"nym:I.O.T.":{"edges":{"from":["territory:IO"]},"meta":{"canonical":false,"canonical-mask":0,"display-name":false,"stable-name":false},"names":{"cy":false,"en-GB":"I.O.T."}},"nym:IO":{"edges":{"from":["territory:IO"]},"meta":{"canonical":false,"canonical-mask":0,"display-name":false,"stable-name":false},"names":{"cy":false,"en-GB":"IO"}},"nym:IOT":{"edges":{"from":["territory:IO"]},"meta":{"canonical":false,"canonical-mask":0,"display-name":false,"stable-name":false},"names":{"cy":false,"en-GB":"IOT"}},"nym:The British Indian Ocean Territory":{"edges":{"from":["territory:IO"]},"meta":{"canonical":false,"canonical-mask":0,"display-name":true,"stable-name":true},"names":{"cy":false,"en-GB":"The British Indian Ocean Territory"}},"territory:IO":{"edges":{"from":[]},"meta":{"canonical":true,"canonical-mask":1,"display-name":true,"stable-name":true},"names":{"cy":false,"en-GB":"British Indian Ocean Territory"}},"nym:Bailiwick of Jersey":{"edges":{"from":["territory:JE"]},"meta":{"canonical":false,"canonical-mask":0,"display-name":true,"stable-name":true},"names":{"cy":false,"en-GB":"Bailiwick of Jersey"}},"nym:Island of Jersey":{"edges":{"from":["territory:JE"]},"meta":{"canonical":false,"canonical-mask":0,"display-name":false,"stable-name":false},"names":{"cy":false,"en-GB":"Island of Jersey"}},"nym:JE":{"edges":{"from":["territory:JE"]},"meta":{"canonical":false,"canonical-mask":0,"display-name":false,"stable-name":false},"names":{"cy":false,"en-GB":"JE"}},"territory:JE":{"edges":{"from":[]},"meta":{"canonical":true,"canonical-mask":1,"display-name":true,"stable-name":true},"names":{"cy":false,"en-GB":"Jersey"}},"nym:Cayman Islands":{"edges":{"from":["territory:KY"]},"meta":{"canonical":false,"canonical-mask":0,"display-name":true,"stable-name":true},"names":{"cy":false,"en-GB":"Cayman Islands"}},"nym:KY":{"edges":{"from":["territory:KY"]},"meta":{"canonical":false,"canonical-mask":0,"display-name":false,"stable-name":false},"names":{"cy":false,"en-GB":"KY"}},"territory:KY":{"edges":{"from":[]},"meta":{"canonical":true,"canonical-mask":1,"display-name":true,"stable-name":true},"names":{"cy":false,"en-GB":"Cayman Islands"}},"nym:Collectivity of Saint Martin":{"edges":{"from":["territory:MF"]},"meta":{"canonical":false,"canonical-mask":0,"display-name":true,"stable-name":true},"names":{"cy":false,"en-GB":"Collectivity of Saint Martin"}},"nym:MF":{"edges":{"from":["territory:MF"]},"meta":{"canonical":false,"canonical-mask":0,"display-name":false,"stable-name":false},"names":{"cy":false,"en-GB":"MF"}},"territory:MF":{"edges":{"from":[]},"meta":{"canonical":true,"canonical-mask":1,"display-name":true,"stable-name":true},"names":{"cy":false,"en-GB":"Saint-Martin (French part)"}},"nym:MO":{"edges":{"from":["territory:MO"]},"meta":{"canonical":false,"canonical-mask":0,"display-name":false,"stable-name":false},"names":{"cy":false,"en-GB":"MO"}},"nym:Macao Special Administrative Region":{"edges":{"from":["territory:MO"]},"meta":{"canonical":false,"canonical-mask":0,"display-name":true,"stable-name":true},"names":{"cy":false,"en-GB":"Macao Special Administrative Region"}},"territory:MO":{"edges":{"from":[]},"meta":{"canonical":true,"canonical-mask":1,"display-name":true,"stable-name":true},"names":{"cy":false,"en-GB":"Macao"}},"nym:Commonwealth of the Northern Mariana Islands":{"edges":{"from":["territory:MP"]},"meta":{"canonical":false,"canonical-mask":0,"display-name":true,"stable-name":true},"names":{"cy":false,"en-GB":"Commonwealth of the Northern Mariana Islands"}},"nym:MP":{"edges":{"from":["territory:MP"]},"meta":{"canonical":false,"canonical-mask":0,"display-name":false,"stable-name":false},"names":{"cy":false,"en-GB":"MP"}},"nym:Northern Marianas":{"edges":{"from":["territory:MP"]},"meta":{"canonical":false,"canonical-mask":0,"display-name":false,"stable-name":false},"names":{"cy":false,"en-GB":"Northern Marianas"}},"territory:MP":{"edges":{"from":[]},"meta":{"canonical":true,"canonical-mask":1,"display-name":true,"stable-name":true},"names":{"cy":false,"en-GB":"Northern Mariana Islands"}},"nym:MQ":{"edges":{"from":["territory:MQ"]},"meta":{"canonical":false,"canonical-mask":0,"display-name":false,"stable-name":false},"names":{"cy":false,"en-GB":"MQ"}},"nym:Martinique":{"edges":{"from":["territory:MQ"]},"meta":{"canonical":false,"canonical-mask":0,"display-name":true,"stable-name":true},"names":{"cy":false,"en-GB":"Martinique"}},"territory:MQ":{"edges":{"from":[]},"meta":{"canonical":true,"canonical-mask":1,"display-name":true,"stable-name":true},"names":{"cy":false,"en-GB":"Martinique"}},"nym:MS":{"edges":{"from":["territory:MS"]},"meta":{"canonical":false,"canonical-mask":0,"display-name":false,"stable-name":false},"names":{"cy":false,"en-GB":"MS"}},"nym:Montserrat":{"edges":{"from":["territory:MS"]},"meta":{"canonical":false,"canonical-mask":0,"display-name":true,"stable-name":true},"names":{"cy":false,"en-GB":"Montserrat"}},"territory:MS":{"edges":{"from":[]},"meta":{"canonical":true,"canonical-mask":1,"display-name":true,"stable-name":true},"names":{"cy":false,"en-GB":"Montserrat"}},"nym:NC":{"edges":{"from":["territory:NC"]},"meta":{"canonical":false,"canonical-mask":0,"display-name":false,"stable-name":false},"names":{"cy":false,"en-GB":"NC"}},"nym:New Caledonia":{"edges":{"from":["territory:NC"]},"meta":{"canonical":false,"canonical-mask":0,"display-name":true,"stable-name":true},"names":{"cy":false,"en-GB":"New Caledonia"}},"nym:Nouvelle-Calédonie":{"edges":{"from":["territory:NC"]},"meta":{"canonical":false,"canonical-mask":0,"display-name":false,"stable-name":false},"names":{"cy":false,"en-GB":"Nouvelle-Calédonie"}},"territory:NC":{"edges":{"from":[]},"meta":{"canonical":true,"canonical-mask":1,"display-name":true,"stable-name":true},"names":{"cy":false,"en-GB":"New Caledonia"}},"nym:NF":{"edges":{"from":["territory:NF"]},"meta":{"canonical":false,"canonical-mask":0,"display-name":false,"stable-name":false},"names":{"cy":false,"en-GB":"NF"}},"nym:Territory of Norfolk Island":{"edges":{"from":["territory:NF"]},"meta":{"canonical":false,"canonical-mask":0,"display-name":true,"stable-name":true},"names":{"cy":false,"en-GB":"Territory of Norfolk Island"}},"territory:NF":{"edges":{"from":[]},"meta":{"canonical":true,"canonical-mask":1,"display-name":true,"stable-name":true},"names":{"cy":false,"en-GB":"Norfolk Island"}},"nym:NU":{"edges":{"from":["territory:NU"]},"meta":{"canonical":false,"canonical-mask":0,"display-name":false,"stable-name":false},"names":{"cy":false,"en-GB":"NU"}},"nym:Niue":{"edges":{"from":["territory:NU"]},"meta":{"canonical":false,"canonical-mask":0,"display-name":false,"stable-name":false},"names":{"cy":false,"en-GB":"Niue"}},"nym:Niuē":{"edges":{"from":["territory:NU"]},"meta":{"canonical":false,"canonical-mask":0,"display-name":false,"stable-name":false},"names":{"cy":false,"en-GB":"Niuē"}},"territory:NU":{"edges":{"from":[]},"meta":{"canonical":true,"canonical-mask":1,"display-name":true,"stable-name":true},"names":{"cy":false,"en-GB":"Niue"}},"nym:French Oceania":{"edges":{"from":["territory:PF"]},"meta":{"canonical":false,"canonical-mask":0,"display-name":false,"stable-name":false},"names":{"cy":false,"en-GB":"French Oceania"}},"nym:French Polynesia":{"edges":{"from":["territory:PF"]},"meta":{"canonical":false,"canonical-mask":0,"display-name":true,"stable-name":true},"names":{"cy":false,"en-GB":"French Polynesia"}},"nym:PF":{"edges":{"from":["territory:PF"]},"meta":{"canonical":false,"canonical-mask":0,"display-name":false,"stable-name":false},"names":{"cy":false,"en-GB":"PF"}},"nym:Polynésie Française":{"edges":{"from":["territory:PF"]},"meta":{"canonical":false,"canonical-mask":0,"display-name":false,"stable-name":false},"names":{"cy":false,"en-GB":"Polynésie Française"}},"nym:Polynésie française":{"edges":{"from":["territory:PF"]},"meta":{"canonical":false,"canonical-mask":0,"display-name":false,"stable-name":false},"names":{"cy":false,"en-GB":"Polynésie française"}},"territory:PF":{"edges":{"from":[]},"meta":{"canonical":true,"canonical-mask":1,"display-name":true,"stable-name":true},"names":{"cy":false,"en-GB":"French Polynesia"}},"nym:PM":{"edges":{"from":["territory:PM"]},"meta":{"canonical":false,"canonical-mask":0,"display-name":false,"stable-name":false},"names":{"cy":false,"en-GB":"PM"}},"nym:Saint Pierre and Miquelon":{"edges":{"from":["territory:PM"]},"meta":{"canonical":false,"canonical-mask":0,"display-name":true,"stable-name":true},"names":{"cy":false,"en-GB":"Saint Pierre and Miquelon"}},"nym:Saint-Pierre et Miquelon":{"edges":{"from":["territory:PM"]},"meta":{"canonical":false,"canonical-mask":0,"display-name":false,"stable-name":false},"names":{"cy":false,"en-GB":"Saint-Pierre et Miquelon"}},"territory:PM":{"edges":{"from":[]},"meta":{"canonical":true,"canonical-mask":1,"display-name":true,"stable-name":true},"names":{"cy":false,"en-GB":"Saint Pierre and Miquelon"}},"nym:Ducie and Oeno Islands":{"edges":{"from":["territory:PN"]},"meta":{"canonical":false,"canonical-mask":0,"display-name":false,"stable-name":false},"names":{"cy":false,"en-GB":"Ducie and Oeno Islands"}},"nym:Henderson":{"edges":{"from":["territory:PN"]},"meta":{"canonical":false,"canonical-mask":0,"display-name":false,"stable-name":false},"names":{"cy":false,"en-GB":"Henderson"}},"nym:PN":{"edges":{"from":["territory:PN"]},"meta":{"canonical":false,"canonical-mask":0,"display-name":false,"stable-name":false},"names":{"cy":false,"en-GB":"PN"}},"nym:Pitcairn":{"edges":{"from":["territory:PN"]},"meta":{"canonical":false,"canonical-mask":0,"display-name":false,"stable-name":false},"names":{"cy":false,"en-GB":"Pitcairn"}},"nym:Pitcairn, Henderson, Ducie and Oeno Islands":{"edges":{"from":["territory:PN"]},"meta":{"canonical":false,"canonical-mask":0,"display-name":true,"stable-name":true},"names":{"cy":false,"en-GB":"Pitcairn, Henderson, Ducie and Oeno Islands"}},"territory:PN":{"edges":{"from":[]},"meta":{"canonical":true,"canonical-mask":1,"display-name":true,"stable-name":true},"names":{"cy":false,"en-GB":"Pitcairn, Henderson, Ducie and Oeno Islands"}},"nym:Commonwealth of Puerto Rico":{"edges":{"from":["territory:PR"]},"meta":{"canonical":false,"canonical-mask":0,"display-name":true,"stable-name":true},"names":{"cy":false,"en-GB":"Commonwealth of Puerto Rico"}},"nym:PR":{"edges":{"from":["territory:PR"]},"meta":{"canonical":false,"canonical-mask":0,"display-name":false,"stable-name":false},"names":{"cy":false,"en-GB":"PR"}},"nym:Porto Rico":{"edges":{"from":["territory:PR"]},"meta":{"canonical":false,"canonical-mask":0,"display-name":false,"stable-name":false},"names":{"cy":false,"en-GB":"Porto Rico"}},"nym:Puarto Rico":{"edges":{"from":["territory:PR"]},"meta":{"canonical":false,"canonical-mask":0,"display-name":false,"stable-name":false},"names":{"cy":false,"en-GB":"Puarto Rico"}},"territory:PR":{"edges":{"from":[]},"meta":{"canonical":true,"canonical-mask":1,"display-name":true,"stable-name":true},"names":{"cy":false,"en-GB":"Puerto Rico"}},"nym:Occupied Palestinian Territories":{"edges":{"from":["territory:PS"]},"meta":{"canonical":false,"canonical-mask":0,"display-name":false,"stable-name":false},"names":{"cy":false,"en-GB":"Occupied Palestinian Territories"}},"nym:PS":{"edges":{"from":["territory:PS"]},"meta":{"canonical":false,"canonical-mask":0,"display-name":false,"stable-name":false},"names":{"cy":false,"en-GB":"PS"}},"nym:The Occupied Palestinian Territories":{"edges":{"from":["territory:PS"]},"meta":{"canonical":false,"canonical-mask":0,"display-name":true,"stable-name":true},"names":{"cy":false,"en-GB":"The Occupied Palestinian Territories"}},"nym:فلسطين":{"edges":{"from":["territory:PS"]},"meta":{"canonical":false,"canonical-mask":0,"display-name":false,"stable-name":false},"names":{"cy":false,"en-GB":"فلسطين"}},"territory:PS":{"edges":{"from":[]},"meta":{"canonical":true,"canonical-mask":1,"display-name":true,"stable-name":true},"names":{"cy":false,"en-GB":"Occupied Palestinian Territories"}},"nym:RE":{"edges":{"from":["territory:RE"]},"meta":{"canonical":false,"canonical-mask":0,"display-name":false,"stable-name":false},"names":{"cy":false,"en-GB":"RE"}},"nym:Reunion":{"edges":{"from":["territory:RE"]},"meta":{"canonical":false,"canonical-mask":0,"display-name":false,"stable-name":false},"names":{"cy":false,"en-GB":"Reunion"}},"nym:Réunion":{"edges":{"from":["territory:RE"]},"meta":{"canonical":false,"canonical-mask":0,"display-name":true,"stable-name":true},"names":{"cy":false,"en-GB":"Réunion"}},"territory:RE":{"edges":{"from":[]},"meta":{"canonical":true,"canonical-mask":1,"display-name":true,"stable-name":true},"names":{"cy":false,"en-GB":"Réunion"}},"nym:Ascension Island":{"edges":{"from":["territory:SH-AC"]},"meta":{"canonical":false,"canonical-mask":0,"display-name":true,"stable-name":true},"names":{"cy":false,"en-GB":"Ascension Island"}},"nym:SH-AC":{"edges":{"from":["territory:SH-AC"]},"meta":{"canonical":false,"canonical-mask":0,"display-name":false,"stable-name":false},"names":{"cy":false,"en-GB":"SH-AC"}},"territory:SH-AC":{"edges":{"from":[]},"meta":{"canonical":true,"canonical-mask":1,"display-name":true,"stable-name":true},"names":{"cy":false,"en-GB":"Ascension"}},"nym:SH-HL":{"edges":{"from":["territory:SH-HL"]},"meta":{"canonical":false,"canonical-mask":0,"display-name":false,"stable-name":false},"names":{"cy":false,"en-GB":"SH-HL"}},"nym:Saint Helena":{"edges":{"from":["territory:SH-HL"]},"meta":{"canonical":false,"canonical-mask":0,"display-name":true,"stable-name":true},"names":{"cy":false,"en-GB":"Saint Helena"}},"territory:SH-HL":{"edges":{"from":[]},"meta":{"canonical":true,"canonical-mask":1,"display-name":true,"stable-name":true},"names":{"cy":false,"en-GB":"Saint Helena"}},"nym:SH-TA":{"edges":{"from":["territory:SH-TA"]},"meta":{"canonical":false,"canonical-mask":0,"display-name":false,"stable-name":false},"names":{"cy":false,"en-GB":"SH-TA"}},"nym:Tristan da Cunha":{"edges":{"from":["territory:SH-TA"]},"meta":{"canonical":false,"canonical-mask":0,"display-name":true,"stable-name":true},"names":{"cy":false,"en-GB":"Tristan da Cunha"}},"territory:SH-TA":{"edges":{"from":[]},"meta":{"canonical":true,"canonical-mask":1,"display-name":true,"stable-name":true},"names":{"cy":false,"en-GB":"Tristan da Cunha"}},"nym:SJ":{"edges":{"from":["territory:SJ"]},"meta":{"canonical":false,"canonical-mask":0,"display-name":false,"stable-name":false},"names":{"cy":false,"en-GB":"SJ"}},"nym:Svalbard and Jan Mayen":{"edges":{"from":["territory:SJ"]},"meta":{"canonical":false,"canonical-mask":0,"display-name":true,"stable-name":true},"names":{"cy":false,"en-GB":"Svalbard and Jan Mayen"}},"territory:SJ":{"edges":{"from":[]},"meta":{"canonical":true,"canonical-mask":1,"display-name":true,"stable-name":true},"names":{"cy":false,"en-GB":"Svalbard and Jan Mayen"}},"nym:SX":{"edges":{"from":["territory:SX"]},"meta":{"canonical":false,"canonical-mask":0,"display-name":false,"stable-name":false},"names":{"cy":false,"en-GB":"SX"}},"nym:Sint Maarten":{"edges":{"from":["territory:SX"]},"meta":{"canonical":false,"canonical-mask":0,"display-name":true,"stable-name":true},"names":{"cy":false,"en-GB":"Sint Maarten"}},"territory:SX":{"edges":{"from":[]},"meta":{"canonical":true,"canonical-mask":1,"display-name":true,"stable-name":true},"names":{"cy":false,"en-GB":"Sint Maarten (Dutch part)"}},"nym:TC":{"edges":{"from":["territory:TC"]},"meta":{"canonical":false,"canonical-mask":0,"display-name":false,"stable-name":false},"names":{"cy":false,"en-GB":"TC"}},"nym:Turks and Caicos Islands":{"edges":{"from":["territory:TC"]},"meta":{"canonical":false,"canonical-mask":0,"display-name":true,"stable-name":true},"names":{"cy":false,"en-GB":"Turks and Caicos Islands"}},"territory:TC":{"edges":{"from":[]},"meta":{"canonical":true,"canonical-mask":1,"display-name":true,"stable-name":true},"names":{"cy":false,"en-GB":"Turks and Caicos Islands"}},"nym:French Southern Territories":{"edges":{"from":["territory:TF"]},"meta":{"canonical":false,"canonical-mask":0,"display-name":true,"stable-name":true},"names":{"cy":false,"en-GB":"French Southern Territories"}},"nym:TF":{"edges":{"from":["territory:TF"]},"meta":{"canonical":false,"canonical-mask":0,"display-name":false,"stable-name":false},"names":{"cy":false,"en-GB":"TF"}},"territory:TF":{"edges":{"from":[]},"meta":{"canonical":true,"canonical-mask":1,"display-name":true,"stable-name":true},"names":{"cy":false,"en-GB":"French Southern Territories"}},"nym:TK":{"edges":{"from":["territory:TK"]},"meta":{"canonical":false,"canonical-mask":0,"display-name":false,"stable-name":false},"names":{"cy":false,"en-GB":"TK"}},"nym:Tokelau":{"edges":{"from":["territory:TK"]},"meta":{"canonical":false,"canonical-mask":0,"display-name":true,"stable-name":true},"names":{"cy":false,"en-GB":"Tokelau"}},"territory:TK":{"edges":{"from":[]},"meta":{"canonical":true,"canonical-mask":1,"display-name":true,"stable-name":true},"names":{"cy":false,"en-GB":"Tokelau"}},"nym:Chinese Taipei":{"edges":{"from":["territory:TW"]},"meta":{"canonical":false,"canonical-mask":0,"display-name":false,"stable-name":false},"names":{"cy":false,"en-GB":"Chinese Taipei"}},"nym:TW":{"edges":{"from":["territory:TW"]},"meta":{"canonical":false,"canonical-mask":0,"display-name":false,"stable-name":false},"names":{"cy":false,"en-GB":"TW"}},"nym:Taiwan":{"edges":{"from":["territory:TW"]},"meta":{"canonical":false,"canonical-mask":0,"display-name":true,"stable-name":true},"names":{"cy":false,"en-GB":"Taiwan"}},"nym:Táiwān":{"edges":{"from":["territory:TW"]},"meta":{"canonical":false,"canonical-mask":0,"display-name":false,"stable-name":false},"names":{"cy":false,"en-GB":"Táiwān"}},"nym:Zhōnghuá Mínguó":{"edges":{"from":["territory:TW"]},"meta":{"canonical":false,"canonical-mask":0,"display-name":false,"stable-name":false},"names":{"cy":false,"en-GB":"Zhōnghuá Mínguó"}},"nym:中華民國":{"edges":{"from":["territory:TW"]},"meta":{"canonical":false,"canonical-mask":0,"display-name":false,"stable-name":false},"names":{"cy":false,"en-GB":"中華民國"}},"nym:台灣":{"edges":{"from":["territory:TW"]},"meta":{"canonical":false,"canonical-mask":0,"display-name":false,"stable-name":false},"names":{"cy":false,"en-GB":"台灣"}},"nym:臺灣":{"edges":{"from":["territory:TW"]},"meta":{"canonical":false,"canonical-mask":0,"display-name":false,"stable-name":false},"names":{"cy":false,"en-GB":"臺灣"}},"nym:臺灣/台灣":{"edges":{"from":["territory:TW"]},"meta":{"canonical":false,"canonical-mask":0,"display-name":false,"stable-name":false},"names":{"cy":false,"en-GB":"臺灣/台灣"}},"territory:TW":{"edges":{"from":[]},"meta":{"canonical":true,"canonical-mask":1,"display-name":true,"stable-name":true},"names":{"cy":false,"en-GB":"Taiwan"}},"nym:Johnston Atoll":{"edges":{"from":["territory:UM-67"]},"meta":{"canonical":false,"canonical-mask":0,"display-name":true,"stable-name":true},"names":{"cy":false,"en-GB":"Johnston Atoll"}},"nym:UM-67":{"edges":{"from":["territory:UM-67"]},"meta":{"canonical":false,"canonical-mask":0,"display-name":false,"stable-name":false},"names":{"cy":false,"en-GB":"UM-67"}},"territory:UM-67":{"edges":{"from":[]},"meta":{"canonical":true,"canonical-mask":1,"display-name":true,"stable-name":true},"names":{"cy":false,"en-GB":"Johnston Atoll"}},"nym:Midway Islands":{"edges":{"from":["territory:UM-71"]},"meta":{"canonical":false,"canonical-mask":0,"display-name":true,"stable-name":true},"names":{"cy":false,"en-GB":"Midway Islands"}},"nym:UM-71":{"edges":{"from":["territory:UM-71"]},"meta":{"canonical":false,"canonical-mask":0,"display-name":false,"stable-name":false},"names":{"cy":false,"en-GB":"UM-71"}},"territory:UM-71":{"edges":{"from":[]},"meta":{"canonical":true,"canonical-mask":1,"display-name":true,"stable-name":true},"names":{"cy":false,"en-GB":"Midway Islands"}},"nym:Navassa Island":{"edges":{"from":["territory:UM-76"]},"meta":{"canonical":false,"canonical-mask":0,"display-name":true,"stable-name":true},"names":{"cy":false,"en-GB":"Navassa Island"}},"nym:UM-76":{"edges":{"from":["territory:UM-76"]},"meta":{"canonical":false,"canonical-mask":0,"display-name":false,"stable-name":false},"names":{"cy":false,"en-GB":"UM-76"}},"territory:UM-76":{"edges":{"from":[]},"meta":{"canonical":true,"canonical-mask":1,"display-name":true,"stable-name":true},"names":{"cy":false,"en-GB":"Navassa Island"}},"territory:UM-79":{"edges":{"from":[]},"meta":{"canonical":true,"canonical-mask":1,"display-name":true,"stable-name":true},"names":{"cy":false,"en-GB":"Wake Island"}},"nym:Baker Island":{"edges":{"from":["territory:UM-81"]},"meta":{"canonical":false,"canonical-mask":0,"display-name":true,"stable-name":true},"names":{"cy":false,"en-GB":"Baker Island"}},"nym:UM-81":{"edges":{"from":["territory:UM-81"]},"meta":{"canonical":false,"canonical-mask":0,"display-name":false,"stable-name":false},"names":{"cy":false,"en-GB":"UM-81"}},"territory:UM-81":{"edges":{"from":[]},"meta":{"canonical":true,"canonical-mask":1,"display-name":true,"stable-name":true},"names":{"cy":false,"en-GB":"Baker Island"}},"nym:Howland Island":{"edges":{"from":["territory:UM-84"]},"meta":{"canonical":false,"canonical-mask":0,"display-name":true,"stable-name":true},"names":{"cy":false,"en-GB":"Howland Island"}},"nym:UM-84":{"edges":{"from":["territory:UM-84"]},"meta":{"canonical":false,"canonical-mask":0,"display-name":false,"stable-name":false},"names":{"cy":false,"en-GB":"UM-84"}},"territory:UM-84":{"edges":{"from":[]},"meta":{"canonical":true,"canonical-mask":1,"display-name":true,"stable-name":true},"names":{"cy":false,"en-GB":"Howland Island"}},"nym:Jarvis Island":{"edges":{"from":["territory:UM-86"]},"meta":{"canonical":false,"canonical-mask":0,"display-name":true,"stable-name":true},"names":{"cy":false,"en-GB":"Jarvis Island"}},"nym:UM-86":{"edges":{"from":["territory:UM-86"]},"meta":{"canonical":false,"canonical-mask":0,"display-name":false,"stable-name":false},"names":{"cy":false,"en-GB":"UM-86"}},"territory:UM-86":{"edges":{"from":[]},"meta":{"canonical":true,"canonical-mask":1,"display-name":true,"stable-name":true},"names":{"cy":false,"en-GB":"Jarvis Island"}},"nym:Kingman Reef":{"edges":{"from":["territory:UM-89"]},"meta":{"canonical":false,"canonical-mask":0,"display-name":true,"stable-name":true},"names":{"cy":false,"en-GB":"Kingman Reef"}},"nym:UM-89":{"edges":{"from":["territory:UM-89"]},"meta":{"canonical":false,"canonical-mask":0,"display-name":false,"stable-name":false},"names":{"cy":false,"en-GB":"UM-89"}},"territory:UM-89":{"edges":{"from":[]},"meta":{"canonical":true,"canonical-mask":1,"display-name":true,"stable-name":true},"names":{"cy":false,"en-GB":"Kingman Reef"}},"nym:Palmyra Atoll":{"edges":{"from":["territory:UM-95"]},"meta":{"canonical":false,"canonical-mask":0,"display-name":true,"stable-name":true},"names":{"cy":false,"en-GB":"Palmyra Atoll"}},"nym:UM-95":{"edges":{"from":["territory:UM-95"]},"meta":{"canonical":false,"canonical-mask":0,"display-name":false,"stable-name":false},"names":{"cy":false,"en-GB":"UM-95"}},"territory:UM-95":{"edges":{"from":[]},"meta":{"canonical":true,"canonical-mask":1,"display-name":true,"stable-name":true},"names":{"cy":false,"en-GB":"Palmyra Atoll"}},"nym:B.V.I.":{"edges":{"from":["territory:VG"]},"meta":{"canonical":false,"canonical-mask":0,"display-name":false,"stable-name":false},"names":{"cy":false,"en-GB":"B.V.I."}},"nym:BVI":{"edges":{"from":["territory:VG"]},"meta":{"canonical":false,"canonical-mask":0,"display-name":false,"stable-name":false},"names":{"cy":false,"en-GB":"BVI"}},"nym:The Virgin Islands":{"edges":{"from":["territory:VG"]},"meta":{"canonical":false,"canonical-mask":0,"display-name":true,"stable-name":true},"names":{"cy":false,"en-GB":"The Virgin Islands"}},"nym:VG":{"edges":{"from":["territory:VG"]},"meta":{"canonical":false,"canonical-mask":0,"display-name":false,"stable-name":false},"names":{"cy":false,"en-GB":"VG"}},"nym:Virgin Islands":{"edges":{"from":["territory:VG"]},"meta":{"canonical":false,"canonical-mask":0,"display-name":false,"stable-name":false},"names":{"cy":false,"en-GB":"Virgin Islands"}},"nym:Virgina Islands":{"edges":{"from":["territory:VG"]},"meta":{"canonical":false,"canonical-mask":0,"display-name":false,"stable-name":false},"names":{"cy":false,"en-GB":"Virgina Islands"}},"territory:VG":{"edges":{"from":[]},"meta":{"canonical":true,"canonical-mask":1,"display-name":true,"stable-name":true},"names":{"cy":false,"en-GB":"British Virgin Islands"}},"nym:American Virgin Islands":{"edges":{"from":["territory:VI"]},"meta":{"canonical":false,"canonical-mask":0,"display-name":false,"stable-name":false},"names":{"cy":false,"en-GB":"American Virgin Islands"}},"nym:VI":{"edges":{"from":["territory:VI"]},"meta":{"canonical":false,"canonical-mask":0,"display-name":false,"stable-name":false},"names":{"cy":false,"en-GB":"VI"}},"nym:Virgin Islands of the United States":{"edges":{"from":["territory:VI"]},"meta":{"canonical":false,"canonical-mask":0,"display-name":true,"stable-name":true},"names":{"cy":false,"en-GB":"Virgin Islands of the United States"}},"territory:VI":{"edges":{"from":[]},"meta":{"canonical":true,"canonical-mask":1,"display-name":true,"stable-name":true},"names":{"cy":false,"en-GB":"United States Virgin Islands"}},"nym:Territory of the Wallis and Futuna Islands":{"edges":{"from":["territory:WF"]},"meta":{"canonical":false,"canonical-mask":0,"display-name":true,"stable-name":true},"names":{"cy":false,"en-GB":"Territory of the Wallis and Futuna Islands"}},"nym:Uvea mo Futuna":{"edges":{"from":["territory:WF"]},"meta":{"canonical":false,"canonical-mask":0,"display-name":false,"stable-name":false},"names":{"cy":false,"en-GB":"Uvea mo Futuna"}},"nym:WF":{"edges":{"from":["territory:WF"]},"meta":{"canonical":false,"canonical-mask":0,"display-name":false,"stable-name":false},"names":{"cy":false,"en-GB":"WF"}},"nym:Wallis-et-Futuna":{"edges":{"from":["territory:WF"]},"meta":{"canonical":false,"canonical-mask":0,"display-name":false,"stable-name":false},"names":{"cy":false,"en-GB":"Wallis-et-Futuna"}},"territory:WF":{"edges":{"from":[]},"meta":{"canonical":true,"canonical-mask":1,"display-name":true,"stable-name":true},"names":{"cy":false,"en-GB":"Wallis and Futuna"}},"nym:XQZ":{"edges":{"from":["territory:XQZ"]},"meta":{"canonical":false,"canonical-mask":0,"display-name":false,"stable-name":false},"names":{"cy":false,"en-GB":"XQZ"}},"territory:XQZ":{"edges":{"from":[]},"meta":{"canonical":true,"canonical-mask":1,"display-name":true,"stable-name":true},"names":{"cy":false,"en-GB":"Akrotiri"}},"nym:Sovereign Base Areas of Akrotiri and Dhekelia":{"edges":{"from":["territory:XXD"]},"meta":{"canonical":false,"canonical-mask":0,"display-name":true,"stable-name":true},"names":{"cy":false,"en-GB":"Sovereign Base Areas of Akrotiri and Dhekelia"}},"nym:XXD":{"edges":{"from":["territory:XXD"]},"meta":{"canonical":false,"canonical-mask":0,"display-name":false,"stable-name":false},"names":{"cy":false,"en-GB":"XXD"}},"territory:XXD":{"edges":{"from":[]},"meta":{"canonical":true,"canonical-mask":1,"display-name":true,"stable-name":true},"names":{"cy":false,"en-GB":"Dhekelia"}},"nym:Mayotte":{"edges":{"from":["territory:YT"]},"meta":{"canonical":false,"canonical-mask":0,"display-name":true,"stable-name":true},"names":{"cy":false,"en-GB":"Mayotte"}},"nym:YT":{"edges":{"from":["territory:YT"]},"meta":{"canonical":false,"canonical-mask":0,"display-name":false,"stable-name":false},"names":{"cy":false,"en-GB":"YT"}},"territory:YT":{"edges":{"from":[]},"meta":{"canonical":true,"canonical-mask":1,"display-name":true,"stable-name":true},"names":{"cy":false,"en-GB":"Mayotte"}}}